DiscordFilter/__init__.py
DiscordFilter-0.0.3.dist-info/METADATA
DiscordFilter-0.0.3.dist-info/WHEEL
DiscordFilter-0.0.3.dist-info/top_level.txt
DiscordFilter-0.0.3.dist-info/RECORD
