Metadata-Version: 2.1
Name: DiscordFilter
Version: 0.0.3
Summary: A Way For Detecting Discord Scams (Updated)
Author: Pirxcy
Classifier: Programming Language :: Python :: 3
Classifier: License :: OSI Approved :: MIT License
Classifier: Operating System :: OS Independent
Requires-Dist: aiohttp
